odoo10_addon_l10n_us_product_stock-10.0.1.0.0-py2.7-nspkg.pth
odoo/addons/l10n_us_product_stock/README.rst
odoo/addons/l10n_us_product_stock/__init__.py
odoo/addons/l10n_us_product_stock/__manifest__.py
odoo/addons/l10n_us_product_stock/views/product_template_view.xml
odoo10_addon_l10n_us_product_stock-10.0.1.0.0.dist-info/DESCRIPTION.rst
odoo10_addon_l10n_us_product_stock-10.0.1.0.0.dist-info/METADATA
odoo10_addon_l10n_us_product_stock-10.0.1.0.0.dist-info/RECORD
odoo10_addon_l10n_us_product_stock-10.0.1.0.0.dist-info/WHEEL
odoo10_addon_l10n_us_product_stock-10.0.1.0.0.dist-info/metadata.json
odoo10_addon_l10n_us_product_stock-10.0.1.0.0.dist-info/namespace_packages.txt
odoo10_addon_l10n_us_product_stock-10.0.1.0.0.dist-info/top_level.txt
