Metadata-Version: 2.0
Name: odoo10-addon-l10n-us-product-stock
Version: 10.0.1.0.0
Summary: This module overrides the product weight and volume to use ounces and cubic inches. It automatically installs if you have l10n_us_product and stock installed.
Home-page: https://laslabs.com/
Author: LasLabs, Odoo Community Association (OCA)
Author-email: support@odoo-community.org
License: LGPL-3
Platform: UNKNOWN
Classifier: Programming Language :: Python
Classifier: Framework :: Odoo
Classifier: License :: OSI Approved :: GNU Lesser General Public License v3 (LGPLv3)
Requires-Python: ~=2.7
Requires-Dist: odoo (<10.1dev,>=10.0)
Requires-Dist: odoo10-addon-l10n-us-product
